cmsplugin_blog_language_publish
