Metadata-Version: 1.0
Name: cmsplugin-blog-language-publish
Version: 0.1.3
Summary: Extension for cmsplugin-blog which allows to only publish certain languages of
